metaflow_extensions/slurm_ext/cmd/mfextinit_slurm_ext.py
metaflow_extensions/slurm_ext/config/mfextinit_slurm_ext.py
metaflow_extensions/slurm_ext/plugins/mfextinit_slurm_ext.py
metaflow_extensions/slurm_ext/plugins/slurm/__init__.py
metaflow_extensions/slurm_ext/plugins/slurm/slurm.py
metaflow_extensions/slurm_ext/plugins/slurm/slurm_cli.py
metaflow_extensions/slurm_ext/plugins/slurm/slurm_client.py
metaflow_extensions/slurm_ext/plugins/slurm/slurm_decorator.py
metaflow_extensions/slurm_ext/plugins/slurm/slurm_exceptions.py
metaflow_extensions/slurm_ext/plugins/slurm/slurm_job.py
metaflow_extensions/slurm_ext/plugins/slurm/slurm_script.py
metaflow_extensions/slurm_ext/toplevel/mfextinit_slurm_ext.py
metaflow_extensions/slurm_ext/toplevel/toplevel.py
metaflow_slurm-0.0.4.dist-info/LICENSE
metaflow_slurm-0.0.4.dist-info/METADATA
metaflow_slurm-0.0.4.dist-info/WHEEL
metaflow_slurm-0.0.4.dist-info/top_level.txt
metaflow_slurm-0.0.4.dist-info/RECORD
